summary_stack_shared/__init__.py
summary_stack_shared/py.typed
summary_stack_shared/models/__init__.py
summary_stack_shared/models/enums.py
summary_stack_shared/models/executive_summary.py
summary_stack_shared/models/passage.py
summary_stack_shared/models/search.py
summary_stack_shared/models/source_metadata.py
summary_stack_shared/models/summary_stack_data.py
summary_stack_shared-0.1.0.dist-info/METADATA
summary_stack_shared-0.1.0.dist-info/WHEEL
summary_stack_shared-0.1.0.dist-info/RECORD
