Metadata-Version: 2.4
Name: summary-stack-shared
Version: 0.1.0
Summary: Shared Pydantic models for Summary Stack backend packages
Project-URL: Homepage, https://summarystack.ai
Project-URL: Repository, https://github.com/tomschreck/cannon-collective-nx
Author-email: Tom Schreck <tom@arta.ing>
License: MIT
Keywords: models,pydantic,summary-stack
Classifier: Development Status :: 4 - Beta
Classifier: Intended Audience :: Developers
Classifier: License :: OSI Approved :: MIT License
Classifier: Programming Language :: Python :: 3
Classifier: Programming Language :: Python :: 3.12
Classifier: Programming Language :: Python :: 3.13
Classifier: Typing :: Typed
Requires-Python: >=3.12
Requires-Dist: pydantic<3.0,>=2.12.0
